{
  "sheetAliases": {
    "export": ["Export", "export", "EXPORT"],
    "helper": ["Segédtábla", "Segedtabla", "segédtábla", "Helper", "Soforok"],
    "leave": ["Szabik 2026", "Szabik2026", "Szabadsag 2026"],
    "roster": ["Munkabeosztás", "Munkabeosztas"]
  },
  "statusMap": {
    "tervezes": "planning",
    "tervezes alatt": "planning",
    "kiosztva": "assigned",
    "kesz": "done",
    "elmaradt": "cancelled"
  },
  "directionMap": {
    "export": "export",
    "exp": "export",
    "import": "import",
    "imp": "import",
    "belfold": "belfold",
    "belföld": "belfold"
  },
  "workPatternMap": {
    "5/2": "5_2",
    "5-2": "5_2",
    "5+2": "5_2",
    "4/3": "4_3",
    "4-3": "4_3",
    "4+3": "4_3",
    "11/3": "11_3",
    "11-3": "11_3",
    "11+3": "11_3",
    "11/2": "11_2",
    "11-2": "11_2",
    "11+2": "11_2",
    "10/3": "10_3",
    "10-3": "10_3",
    "10+3": "10_3",
    "10/4": "10_4",
    "10-4": "10_4",
    "10+4": "10_4",
    "17/4": "17_4",
    "17-4": "17_4",
    "17+4": "17_4",
    "2/1": "2_1",
    "2/1.": "2_1",
    "1/1": "1_1",
    "1/1.": "1_1",
    "6/1": "6_1",
    "6-1": "6_1"
  },
  "exportMapping": {
    "fuvar id": "jobId",
    "fuvar szam": "jobId",
    "fuvar tipus": "direction",
    "statusz": "status",
    "status": "status",
    "tervezett indulas": "pickupAt",
    "tervezett indulás": "pickupAt",
    "tervezett erkezes": "dropoffAt",
    "tervezett érkezés": "dropoffAt",
    "felrako cim": "pickupAddress",
    "felrakó cím": "pickupAddress",
    "lerako cim": "dropoffAddress",
    "lerakó cím": "dropoffAddress",
    "km": "distanceKm",
    "adr": "adrRequired",
    "kezszam": "requiredHands",
    "kézszám": "requiredHands",
    "menetiranyitasi egyseg": "dispatchUnit",
    "menetirányítási egység": "dispatchUnit",
    "partner referencia": "partnerReference",
    "akasztasi magassag": "hookHeightMm",
    "akasztási magasság": "hookHeightMm",
    "tranzit ido": "plannedTransitMinutes",
    "tranzit idő": "plannedTransitMinutes",
    "vezetesi ido": "plannedDrivingMinutes",
    "vezetési idő": "plannedDrivingMinutes",
    "megjegyzes": "note",
    "megjegyzés": "note"
  },
  "helperMapping": {
    "sofor id": "driverId",
    "sofor neve": "name",
    "adr jogosultsag": "adrQualified",
    "adr jogosultság": "adrQualified",
    "munkarend": "workPatternCode",
    "ciklus kezdonap": "cycleAnchorDate",
    "ciklus kezdőnap": "cycleAnchorDate",
    "dedikalt rendszam": "dedicatedVehiclePlate",
    "dedikált rendszám": "dedicatedVehiclePlate",
    "preferalt orszagok": "preferredCountries",
    "preferált országok": "preferredCountries",
    "nem preferalt orszagok": "blockedCountries",
    "nem preferált országok": "blockedCountries",
    "rovid munka vallalas": "shortShiftAllowed",
    "rövid munka vállalás": "shortShiftAllowed",
    "hetvegi vallalas max": "maxWeekendCommitments",
    "hétvégi vállalás max": "maxWeekendCommitments",
    "aktiv": "active"
  },
  "exportAssignmentMapping": {
    "mi neve": "workPatternCode",
    "vontato rendszam": "vehiclePlate",
    "sofor ok": "driverNames",
    "szf szam": "jobId",
    "jani megjegyzes": "plannerNote",
    "menetiranyito megjegyzes erkezes heti maradek ido mikor szeretne ind hetvege kint 24 v 45 kell e": "dispatchNote"
  },
  "helperActualMapping": {
    "rendszam": "dedicatedVehiclePlate",
    "nemzetkozi sofor ok": "name",
    "munkarend": "workPatternCode",
    "idorend": "scheduleNote",
    "preferalt orszag": "preferredCountries",
    "nem preferalt orszag": "blockedCountries",
    "elohuzni tudunk neki": "shortShiftAllowed",
    "megjegyzes hetvegehez": "weekendNote",
    "vonatot vallal": "trainEligible",
    "adr": "adrQualified",
    "didb": "doubleDeckQualified",
    "fulke tipus": "cabType",
    "kerekmeret": "wheelSize",
    "tl": "note"
  },
  "leaveMarkers": {
    "x": "ON_LEAVE",
    "sz": "ON_LEAVE",
    "sza": "ON_LEAVE",
    "b": "SICK_LEAVE",
    "p": "REST"
  },
  "skipCellValues": ["#n/a", "n/a", "-", ""]
}
